cursor_pagination.py
django_cursor_pagination-0.2.0.dist-info/LICENSE
django_cursor_pagination-0.2.0.dist-info/METADATA
django_cursor_pagination-0.2.0.dist-info/WHEEL
django_cursor_pagination-0.2.0.dist-info/top_level.txt
django_cursor_pagination-0.2.0.dist-info/RECORD
