Metadata-Version: 2.1
Name: django-cursor-pagination
Version: 0.2.0
Summary: Cursor based pagination for Django
Home-page: https://github.com/photocrowd/django-cursor-pagination
Author: Photocrowd
Author-email: devteam@photocrowd.com
License: BSD
Classifier: Development Status :: 2 - Pre-Alpha
Classifier: Framework :: Django
Classifier: Intended Audience :: Developers
Classifier: License :: OSI Approved :: BSD License
Classifier: Natural Language :: English
Classifier: Programming Language :: Python :: 3
Classifier: Programming Language :: Python :: 3.7
Classifier: Programming Language :: Python :: 3.8
Classifier: Programming Language :: Python :: 3.9
Classifier: Programming Language :: Python :: 3.10
License-File: LICENSE
